fibertools/__init__.py
fibertools/add_nucleosomes.py
fibertools/classify.py
fibertools/cli.py
fibertools/fiberdata.py
fibertools/fibertools.py
fibertools/readutils.py
fibertools/trackhub.py
fibertools/unionbg.py
fibertools/utils.py
fibertools-0.3.0.dist-info/AUTHORS.rst
fibertools-0.3.0.dist-info/LICENSE
fibertools-0.3.0.dist-info/METADATA
fibertools-0.3.0.dist-info/WHEEL
fibertools-0.3.0.dist-info/entry_points.txt
fibertools-0.3.0.dist-info/top_level.txt
fibertools-0.3.0.dist-info/RECORD
