Metadata-Version: 2.1
Name: fibertools
Version: 0.3.0
Summary: A project for handling fiber-seq data.
Home-page: https://github.com/mrvollger/fibertools
Author: Mitchell R. Vollger
Author-email: mrvollger@gmail.com
License: MIT license
Keywords: fibertools
Classifier: Development Status :: 2 - Pre-Alpha
Classifier: Intended Audience :: Developers
Classifier: License :: OSI Approved :: MIT License
Classifier: Natural Language :: English
Classifier: Programming Language :: Python :: 3
Classifier: Programming Language :: Python :: 3.6
Classifier: Programming Language :: Python :: 3.7
Classifier: Programming Language :: Python :: 3.8
Classifier: Programming Language :: Python :: 3.9
Requires-Python: >=3.6
License-File: LICENSE
License-File: AUTHORS.rst
Requires-Dist: sphinx (==4.2.0)
Requires-Dist: docutils (==0.17)
Requires-Dist: rstcheck (==5.0.0)
Requires-Dist: numpy (==1.23.1)
Requires-Dist: numba
Requires-Dist: pandas (>=1.4)
Requires-Dist: pysam (>=0.19.0)
Requires-Dist: pyranges (>=0.0.115)
Requires-Dist: mokapot (==0.8)
Requires-Dist: scikit-learn
Requires-Dist: xgboost (==1.5.1)
Requires-Dist: Cython
Requires-Dist: pyarrow
Requires-Dist: tqdm
Requires-Dist: pip (>=20.1)
Requires-Dist: sorted-nearest
Requires-Dist: bumpversion
Requires-Dist: psutil
Requires-Dist: polars (==0.14)
Requires-Dist: pyd4 (>=0.3.6.2)
Requires-Dist: pomegranate (>=0.14.8)
